omero_3Dscript/__init__.py
omero_3Dscript/apps.py
omero_3Dscript/fiji.py
omero_3Dscript/omero_3Dscript_settings.py
omero_3Dscript/urls.py
omero_3Dscript/views.py
omero_3Dscript/static/3Dscript/3rdparty/backbone-1.4.0.min.js
omero_3Dscript/static/3Dscript/3rdparty/ome.csrf.js
omero_3Dscript/static/3Dscript/3rdparty/svg.min.js
omero_3Dscript/static/3Dscript/3rdparty/textarea-caret-position.js
omero_3Dscript/static/3Dscript/3rdparty/underscore-1.9.1.min.js
omero_3Dscript/static/3Dscript/3rdparty/jquery-ui-1.12.1/AUTHORS.txt
omero_3Dscript/static/3Dscript/3rdparty/jquery-ui-1.12.1/LICENSE.txt
omero_3Dscript/static/3Dscript/3rdparty/jquery-ui-1.12.1/index.html
omero_3Dscript/static/3Dscript/3rdparty/jquery-ui-1.12.1/jquery-ui.css
omero_3Dscript/static/3Dscript/3rdparty/jquery-ui-1.12.1/jquery-ui.js
omero_3Dscript/static/3Dscript/3rdparty/jquery-ui-1.12.1/jquery-ui.min.css
omero_3Dscript/static/3Dscript/3rdparty/jquery-ui-1.12.1/jquery-ui.min.js
omero_3Dscript/static/3Dscript/3rdparty/jquery-ui-1.12.1/jquery-ui.structure.css
omero_3Dscript/static/3Dscript/3rdparty/jquery-ui-1.12.1/jquery-ui.structure.min.css
omero_3Dscript/static/3Dscript/3rdparty/jquery-ui-1.12.1/jquery-ui.theme.css
omero_3Dscript/static/3Dscript/3rdparty/jquery-ui-1.12.1/jquery-ui.theme.min.css
omero_3Dscript/static/3Dscript/3rdparty/jquery-ui-1.12.1/package.json
omero_3Dscript/static/3Dscript/3rdparty/jquery-ui-1.12.1/external/jquery/jquery.js
omero_3Dscript/static/3Dscript/3rdparty/jquery-ui-1.12.1/images/ui-icons_444444_256x240.png
omero_3Dscript/static/3Dscript/3rdparty/jquery-ui-1.12.1/images/ui-icons_555555_256x240.png
omero_3Dscript/static/3Dscript/3rdparty/jquery-ui-1.12.1/images/ui-icons_777620_256x240.png
omero_3Dscript/static/3Dscript/3rdparty/jquery-ui-1.12.1/images/ui-icons_777777_256x240.png
omero_3Dscript/static/3Dscript/3rdparty/jquery-ui-1.12.1/images/ui-icons_cc0000_256x240.png
omero_3Dscript/static/3Dscript/3rdparty/jquery-ui-1.12.1/images/ui-icons_ffffff_256x240.png
OMERO_3Dscript-0.0.10.dist-info/LICENSE
OMERO_3Dscript-0.0.10.dist-info/METADATA
OMERO_3Dscript-0.0.10.dist-info/WHEEL
OMERO_3Dscript-0.0.10.dist-info/top_level.txt
OMERO_3Dscript-0.0.10.dist-info/RECORD
