Metadata-Version: 2.1
Name: OMERO-3Dscript
Version: 0.0.10
Summary: OMERO.web app to animate multi-dimensional microscopy using 3Dscript, directly from within the OMERO environment.
Home-page: https://github.com/bene51/omero_3Dscript
Author: Benjamin Schmid
Author-email: bene.schmid@gmail.com
License: AGPL-3.0
Keywords: OMERO.web,3Dscript,animation,3D
Classifier: Development Status :: 3 - Alpha
Classifier: Environment :: GPU
Classifier: Environment :: Web Environment
Classifier: Framework :: Django
Classifier: Intended Audience :: End Users/Desktop
Classifier: Intended Audience :: Science/Research
Classifier: Natural Language :: English
Classifier: Operating System :: OS Independent
Classifier: Programming Language :: JavaScript
Classifier: Programming Language :: Python :: 3
Classifier: Topic :: Internet :: WWW/HTTP
Classifier: Topic :: Internet :: WWW/HTTP :: Dynamic Content
Classifier: Topic :: Internet :: WWW/HTTP :: WSGI
Classifier: Topic :: Multimedia :: Graphics :: 3D Rendering
Classifier: Topic :: Multimedia :: Video
Classifier: Topic :: Scientific/Engineering :: Visualization
Requires-Python: >=3
License-File: LICENSE
Requires-Dist: omero-web >=5.6.0
Requires-Dist: pid
